MANIFEST.in
README.md
ntnu-process-mining.json
setup.cfg
setup.py
ntnu_process_mining/__init__.py
ntnu_process_mining/_version.py
ntnu_process_mining.egg-info/PKG-INFO
ntnu_process_mining.egg-info/SOURCES.txt
ntnu_process_mining.egg-info/dependency_links.txt
ntnu_process_mining.egg-info/not-zip-safe
ntnu_process_mining.egg-info/requires.txt
ntnu_process_mining.egg-info/top_level.txt
ntnu_process_mining/static/extension.js
ntnu_process_mining/static/index.js
ntnu_process_mining/static/index.js.map
ntnu_process_mining/utils/__init__.py
ntnu_process_mining/utils/events_to_traces.py
ntnu_process_mining/widgets/__init__.py
ntnu_process_mining/widgets/process_map.py
ntnu_process_mining/widgets/trace_comparison.py
ntnu_process_mining/widgets/trace_explorer.py